otest/__init__.py
otest/main.py
otest_oriont-0.0.2.dist-info/LICENCE
otest_oriont-0.0.2.dist-info/METADATA
otest_oriont-0.0.2.dist-info/WHEEL
otest_oriont-0.0.2.dist-info/top_level.txt
otest_oriont-0.0.2.dist-info/RECORD
